Django2ByExampleZhongwenban/README.md
Django2ByExampleZhongwenban/__init__.py
Django2ByExampleZhongwenban/__main__.py
Django2ByExampleZhongwenban/file.epub
Django2ByExampleZhongwenban/index.html
Django2ByExampleZhongwenban/css/__init__.py
Django2ByExampleZhongwenban/css/annotations.css
Django2ByExampleZhongwenban/css/main.css
Django2ByExampleZhongwenban/css/normalize.css
Django2ByExampleZhongwenban/css/popup.css
Django2ByExampleZhongwenban/font/__init__.py
Django2ByExampleZhongwenban/font/fontello.eot
Django2ByExampleZhongwenban/font/fontello.svg
Django2ByExampleZhongwenban/font/fontello.ttf
Django2ByExampleZhongwenban/font/fontello.woff
Django2ByExampleZhongwenban/img/__init__.py
Django2ByExampleZhongwenban/img/annotator-glyph-sprite.png
Django2ByExampleZhongwenban/img/annotator-icon-sprite.png
Django2ByExampleZhongwenban/img/apple-touch-icon.png
Django2ByExampleZhongwenban/img/cancelfullscreen.png
Django2ByExampleZhongwenban/img/close.png
Django2ByExampleZhongwenban/img/fullscreen.png
Django2ByExampleZhongwenban/img/loader.gif
Django2ByExampleZhongwenban/img/menu-icon.png
Django2ByExampleZhongwenban/img/save.png
Django2ByExampleZhongwenban/img/saved.png
Django2ByExampleZhongwenban/img/settings-s.png
Django2ByExampleZhongwenban/img/settings.png
Django2ByExampleZhongwenban/img/star.png
Django2ByExampleZhongwenban/js/__init__.py
Django2ByExampleZhongwenban/js/epub.js
Django2ByExampleZhongwenban/js/epub.min.js
Django2ByExampleZhongwenban/js/epub.min.map
Django2ByExampleZhongwenban/js/hooks.min.js
Django2ByExampleZhongwenban/js/hooks.min.map
Django2ByExampleZhongwenban/js/reader.js
Django2ByExampleZhongwenban/js/reader.js.map
Django2ByExampleZhongwenban/js/reader.min.js
Django2ByExampleZhongwenban/js/reader.min.map
Django2ByExampleZhongwenban/js/hooks/__init__.py
Django2ByExampleZhongwenban/js/hooks/extensions/__init__.py
Django2ByExampleZhongwenban/js/hooks/extensions/highlight.js
Django2ByExampleZhongwenban/js/libs/__init__.py
django_2_by_example_zhongwenban-2024.3.3.0.dist-info/METADATA
django_2_by_example_zhongwenban-2024.3.3.0.dist-info/WHEEL
django_2_by_example_zhongwenban-2024.3.3.0.dist-info/entry_points.txt
django_2_by_example_zhongwenban-2024.3.3.0.dist-info/top_level.txt
django_2_by_example_zhongwenban-2024.3.3.0.dist-info/RECORD
